git_code_counter/__init__.py
git_code_counter/cli.py
git_code_counter/git_code_counter.py
git_code_counter-0.1.2.dist-info/AUTHORS.rst
git_code_counter-0.1.2.dist-info/LICENSE
git_code_counter-0.1.2.dist-info/METADATA
git_code_counter-0.1.2.dist-info/WHEEL
git_code_counter-0.1.2.dist-info/entry_points.txt
git_code_counter-0.1.2.dist-info/top_level.txt
git_code_counter-0.1.2.dist-info/RECORD
